argstat/__init__.py
argstat/argstat.py
argstat/test_argstat.py
argstat-0.1.0.dist-info/METADATA
argstat-0.1.0.dist-info/RECORD
argstat-0.1.0.dist-info/WHEEL
argstat-0.1.0.dist-info/top_level.txt
