Metadata-Version: 2.1
Name: argstat
Version: 0.1.0
Summary: Beutiful printer for arguments
Home-page: https://github.com/sisobus/argstat
Author: Sangkeun Kim
Author-email: sisobus1@gmail.com
License: MIT
Keywords: pretty argparse argstat
Platform: UNKNOWN
Classifier: Development Status :: 3 - Alpha
Classifier: Intended Audience :: Developers
Classifier: Topic :: Software Development :: Libraries
Classifier: License :: OSI Approved :: MIT License
Classifier: Programming Language :: Python :: 2
Classifier: Programming Language :: Python :: 2.7
Classifier: Programming Language :: Python :: 3
Classifier: Programming Language :: Python :: 3.0
Classifier: Programming Language :: Python :: 3.1
Classifier: Programming Language :: Python :: 3.2
Classifier: Programming Language :: Python :: 3.3
Classifier: Programming Language :: Python :: 3.4
Classifier: Programming Language :: Python :: 3.5
Classifier: Programming Language :: Python :: 3.6
Classifier: Programming Language :: Python :: 3.7
Requires-Dist: six (>=1.7)
Requires-Dist: blessings (>=1.6)
